qhronology/__init__.py
qhronology/mechanics/__init__.py
qhronology/mechanics/matrices.py
qhronology/mechanics/operations.py
qhronology/mechanics/quantities.py
qhronology/quantum/__init__.py
qhronology/quantum/circuits.py
qhronology/quantum/gates.py
qhronology/quantum/prescriptions.py
qhronology/quantum/states.py
qhronology/utilities/__init__.py
qhronology/utilities/classification.py
qhronology/utilities/diagrams.py
qhronology/utilities/helpers.py
qhronology/utilities/objects.py
qhronology/utilities/symbolics.py
qhronology-1.0.2.dist-info/licenses/LICENSE
qhronology-1.0.2.dist-info/METADATA
qhronology-1.0.2.dist-info/WHEEL
qhronology-1.0.2.dist-info/top_level.txt
qhronology-1.0.2.dist-info/RECORD
