Metadata-Version: 2.4
Name: qhronology
Version: 1.0.2
Summary: A Python package for studying quantum models of closed timelike curves and simulating general quantum information processing & computation
Author-email: "Lachlan G. Bishop" <lachlanbishop@protonmail.com>
Maintainer-email: lgbishop <lachlanbishop@protonmail.com>
License-Expression: AGPL-3.0-or-later OR LicenseRef-Custom-Commercial-License-Agreement
Project-URL: Documentation, https://qhronology.com
Project-URL: Repository, https://github.com/lgbishop/qhronology
Project-URL: Download, https://github.com/lgbishop/qhronology/releases
Classifier: Development Status :: 4 - Beta
Classifier: Intended Audience :: Science/Research
Classifier: Programming Language :: Python
Classifier: Programming Language :: Python :: 3
Classifier: Programming Language :: Python :: 3.11
Classifier: Programming Language :: Python :: 3.12
Classifier: Programming Language :: Python :: 3.13
Classifier: Programming Language :: Python :: 3.14
Classifier: Programming Language :: Python :: 3.15
Classifier: Programming Language :: Python :: 3 :: Only
Classifier: Topic :: Scientific/Engineering
Classifier: Topic :: Scientific/Engineering :: Physics
Classifier: Topic :: Scientific/Engineering :: Quantum Computing
Classifier: Operating System :: Unix
Classifier: Operating System :: POSIX
Classifier: Operating System :: POSIX :: Linux
Classifier: Operating System :: Microsoft :: Windows
Requires-Python: >=3.11
License-File: LICENSE
Requires-Dist: sympy>=1.12
Requires-Dist: numpy>=1.26
Dynamic: license-file
